wooting_rgb/__init__.py
wooting_rgb/wooting_rgb.py
wooting_rgb/wooting_rgb_wrapper.py
wooting_rgb-0.0.1.data/scripts/wooting_rgb_reset.py
wooting_rgb-0.0.1.dist-info/LICENSE.txt
wooting_rgb-0.0.1.dist-info/METADATA
wooting_rgb-0.0.1.dist-info/WHEEL
wooting_rgb-0.0.1.dist-info/top_level.txt
wooting_rgb-0.0.1.dist-info/RECORD
