Metadata-Version: 2.1
Name: wooting-rgb
Version: 0.0.1
Summary: Python bindings for Wooting RGB SDK
Home-page: UNKNOWN
Author: Alcasa
Author-email: alcasa@arsbrevis.de
License: LICENSE.txt
Platform: UNKNOWN
License-File: LICENSE.txt
